optiviz/__init__.py
optiviz/optimise.py
optiviz/visualise.py
optiviz-0.1.4.dist-info/licenses/LICENSE.txt
optiviz-0.1.4.dist-info/METADATA
optiviz-0.1.4.dist-info/WHEEL
optiviz-0.1.4.dist-info/top_level.txt
optiviz-0.1.4.dist-info/RECORD
