Metadata-Version: 2.4
Name: optiviz
Version: 0.1.4
Summary: Educational tool for visualizing PyTorch-compatible optimisers on any differentiable 1D or 2D function.
Author-email: Ronit Kunkolienker <ronitkunk@gmail.com>
License: MIT License
Requires-Python: >=3.8
License-File: LICENSE.txt
Requires-Dist: torch
Requires-Dist: matplotlib
Requires-Dist: numpy
Dynamic: license-file
